lagrange/__init__.py
lagrange/__init__.pyi
lagrange/_logging.py
lagrange/_version.py
lagrange/bvh.pyi
lagrange/core.pyi
lagrange/filtering.pyi
lagrange/geodesic.pyi
lagrange/image.pyi
lagrange/io.pyi
lagrange/lagrange.cpython-313-x86_64-linux-gnu.so
lagrange/libtbb.so
lagrange/libtbb.so.12
lagrange/libtbb.so.12.17
lagrange/poisson.pyi
lagrange/polyddg.pyi
lagrange/primitive.pyi
lagrange/py.typed
lagrange/scene.pyi
lagrange/solver.pyi
lagrange/subdivision.pyi
lagrange/texproc.pyi
lagrange_open-6.40.1.data/scripts/extract_texture.py
lagrange_open-6.40.1.data/scripts/geodesic_dilation.py
lagrange_open-6.40.1.data/scripts/mesh_subdivision.py
lagrange_open-6.40.1.data/scripts/meshconvert.py
lagrange_open-6.40.1.data/scripts/meshstat.py
lagrange_open-6.40.1.data/scripts/poisson_recon.py
lagrange_open-6.40.1.data/scripts/texture_from_multiview.py
lagrange_open-6.40.1.dist-info/METADATA
lagrange_open-6.40.1.dist-info/WHEEL
lagrange_open-6.40.1.dist-info/RECORD
lagrange_open-6.40.1.dist-info/licenses/LICENSE
lagrange_open-6.40.1.dist-info/licenses/NOTICE.txt
