Metadata-Version: 2.4
Name: lagrange-open
Version: 6.40.1
Summary: A robust geometry processing engine
Maintainer-Email: Lagrange Core Team <lagrange-core@adobe.com>
License-Expression: Apache-2.0
License-File: LICENSE
License-File: NOTICE.txt
Classifier: Development Status :: 5 - Production/Stable
Classifier: Intended Audience :: Science/Research
Classifier: Programming Language :: C++
Classifier: Programming Language :: Python :: 3 :: Only
Classifier: Programming Language :: Python :: 3.10
Classifier: Programming Language :: Python :: 3.11
Classifier: Programming Language :: Python :: 3.12
Classifier: Programming Language :: Python :: 3.13
Classifier: Programming Language :: Python :: 3.14
Classifier: Topic :: Multimedia :: Graphics :: 3D Modeling
Project-URL: documentation, https://opensource.adobe.com/lagrange-docs
Project-URL: repository, https://github.com/adobe/lagrange
Requires-Python: >=3.10
Requires-Dist: colorama>=0.4.4; platform_system != "Windows"
Requires-Dist: colorama>=0.4.6; platform_system == "Windows"
Requires-Dist: numpy>=1.25
Requires-Dist: scipy>=1.13.0
Provides-Extra: docs
Requires-Dist: furo==2025.9.25; python_version >= "3.12" and extra == "docs"
Requires-Dist: sphinx==8.2.3; python_version >= "3.12" and extra == "docs"
Requires-Dist: sphinx-autoapi==3.6.1; python_version >= "3.12" and extra == "docs"
Requires-Dist: sphinx-autodoc-typehints==3.5.2; python_version >= "3.12" and extra == "docs"
Provides-Extra: scripts
Requires-Dist: pillow>=10.0.0; extra == "scripts"
Requires-Dist: pyexr>=0.5.0; extra == "scripts"
Requires-Dist: pymcubes==0.1.6; extra == "scripts"
Requires-Dist: torch>=2.2.0; extra == "scripts"
